{
  "parent_bank_statement_id": 1532,
  "parent_info": {
    "file_name": "bank_file_61",
    "file_hash": "reconcile_bank_1767849399_1968",
    "upload_timestamp": "2026-01-08 10:46:39",
    "source": "reconciliation_endpoint"
  },
  "all_extracted_records": [
    {
      "record_id": 1,
      "transaction_date": "22 Apr 2024",
      "description": "22 Apr 2024 Direct Debit TESCO MOBILE / ref: 330174659056A-0010 51.49 1,693.87",
      "amount": 51.49,
      "currency": "£",
      "file_name": null
    }
  ],
  "extraction_metadata": {
    "total_records": 1,
    "total_credits": 51.49,
    "total_debits": 0,
    "extraction_confidence": 0.85,
    "processed_at": "2026-01-08 10:46:39",
    "source": "reconciliation_endpoint"
  }
}